taman/__init__.py
taman/api.py
taman/cli.py
taman/config.py
taman/main.py
taman/main_new.py
taman/.venv/Lib/site-packages/_virtualenv.py
taman/.venv/Lib/site-packages/pythoncom.py
taman/.venv/Lib/site-packages/typing_extensions.py
taman/.venv/Lib/site-packages/wmi.py
taman/.venv/Lib/site-packages/adodbapi/__init__.py
taman/.venv/Lib/site-packages/adodbapi/ado_consts.py
taman/.venv/Lib/site-packages/adodbapi/adodbapi.py
taman/.venv/Lib/site-packages/adodbapi/apibase.py
taman/.venv/Lib/site-packages/adodbapi/is64bit.py
taman/.venv/Lib/site-packages/adodbapi/process_connect_string.py
taman/.venv/Lib/site-packages/adodbapi/schema_table.py
taman/.venv/Lib/site-packages/adodbapi/setup.py
taman/.venv/Lib/site-packages/adodbapi/examples/db_print.py
taman/.venv/Lib/site-packages/adodbapi/examples/db_table_names.py
taman/.venv/Lib/site-packages/adodbapi/examples/xls_read.py
taman/.venv/Lib/site-packages/adodbapi/examples/xls_write.py
taman/.venv/Lib/site-packages/adodbapi/test/adodbapitest.py
taman/.venv/Lib/site-packages/adodbapi/test/adodbapitestconfig.py
taman/.venv/Lib/site-packages/adodbapi/test/dbapi20.py
taman/.venv/Lib/site-packages/adodbapi/test/is64bit.py
taman/.venv/Lib/site-packages/adodbapi/test/setuptestframework.py
taman/.venv/Lib/site-packages/adodbapi/test/test_adodbapi_dbapi20.py
taman/.venv/Lib/site-packages/adodbapi/test/tryconnection.py
taman/.venv/Lib/site-packages/annotated_types/__init__.py
taman/.venv/Lib/site-packages/annotated_types/test_cases.py
taman/.venv/Lib/site-packages/anyio/__init__.py
taman/.venv/Lib/site-packages/anyio/from_thread.py
taman/.venv/Lib/site-packages/anyio/lowlevel.py
taman/.venv/Lib/site-packages/anyio/pytest_plugin.py
taman/.venv/Lib/site-packages/anyio/to_interpreter.py
taman/.venv/Lib/site-packages/anyio/to_process.py
taman/.venv/Lib/site-packages/anyio/to_thread.py
taman/.venv/Lib/site-packages/anyio/_backends/__init__.py
taman/.venv/Lib/site-packages/anyio/_backends/_asyncio.py
taman-0.1.0.dist-info/licenses/LICENSE
taman-0.1.0.dist-info/METADATA
taman-0.1.0.dist-info/WHEEL
taman-0.1.0.dist-info/entry_points.txt
taman-0.1.0.dist-info/top_level.txt
taman-0.1.0.dist-info/RECORD
